nixgateway/__init__.py
nixgateway/api.py
nixgateway-0.8.dist-info/DESCRIPTION.rst
nixgateway-0.8.dist-info/METADATA
nixgateway-0.8.dist-info/RECORD
nixgateway-0.8.dist-info/WHEEL
nixgateway-0.8.dist-info/metadata.json
nixgateway-0.8.dist-info/top_level.txt
