Metadata-Version: 2.0
Name: nixgateway
Version: 0.8
Summary: Python bindings to the Nix Gateway API (https://web-nix.cloud.nexxera.com/)
Home-page: https://github.com/scardine/py-nixgateway
Author: Paulo Scardine
Author-email: paulos@xtend.com.br
License: UNKNOWN
Download-URL: https://github.com/scardine/py-nixgateway/archive/0.8.tar.gz
Keywords: nexxera,nix gateway,payments,api
Platform: UNKNOWN
Requires-Dist: python-jose
Requires-Dist: requests
